biobeaker/Beaker.py
biobeaker/__init__.py
biobeaker/utils.py
biobeaker-0.0.2.dist-info/WHEEL
biobeaker-0.0.2.dist-info/METADATA
biobeaker-0.0.2.dist-info/RECORD
