Metadata-Version: 2.1
Name: biobeaker
Version: 0.0.2
Summary: Coming soon
Home-page: https://github.com/jguhlin/beaker
License: TBD
Keywords: machine learning,bioinformatics
Author: Joseph Guhlin
Author-email: joseph.guhlin@gmail.com
Requires-Python: >=3.7,<3.9
Classifier: License :: Other/Proprietary License
Classifier: Programming Language :: Python :: 3
Classifier: Programming Language :: Python :: 3.7
Classifier: Programming Language :: Python :: 3.8
Classifier: Topic :: Scientific/Engineering :: Bio-Informatics
Requires-Dist: baseconvert (==1.0.0.a4)
Requires-Dist: numpy (==1.19.2)
Requires-Dist: tensorflow (==2.4.1)
Requires-Dist: tensorflow-addons (==0.12.1)
Project-URL: Documentation, https://github.com/jguhlin/beaker
Project-URL: Repository, https://github.com/jguhlin/beaker
